DongshouXueShenduXuexiPytorchBan2020313Fix1/README.md
DongshouXueShenduXuexiPytorchBan2020313Fix1/__init__.py
DongshouXueShenduXuexiPytorchBan2020313Fix1/__main__.py
DongshouXueShenduXuexiPytorchBan2020313Fix1/file.epub
DongshouXueShenduXuexiPytorchBan2020313Fix1/index.html
DongshouXueShenduXuexiPytorchBan2020313Fix1/css/__init__.py
DongshouXueShenduXuexiPytorchBan2020313Fix1/css/annotations.css
DongshouXueShenduXuexiPytorchBan2020313Fix1/css/main.css
DongshouXueShenduXuexiPytorchBan2020313Fix1/css/normalize.css
DongshouXueShenduXuexiPytorchBan2020313Fix1/css/popup.css
DongshouXueShenduXuexiPytorchBan2020313Fix1/font/__init__.py
DongshouXueShenduXuexiPytorchBan2020313Fix1/font/fontello.eot
DongshouXueShenduXuexiPytorchBan2020313Fix1/font/fontello.svg
DongshouXueShenduXuexiPytorchBan2020313Fix1/font/fontello.ttf
DongshouXueShenduXuexiPytorchBan2020313Fix1/font/fontello.woff
DongshouXueShenduXuexiPytorchBan2020313Fix1/img/__init__.py
DongshouXueShenduXuexiPytorchBan2020313Fix1/img/annotator-glyph-sprite.png
DongshouXueShenduXuexiPytorchBan2020313Fix1/img/annotator-icon-sprite.png
DongshouXueShenduXuexiPytorchBan2020313Fix1/img/apple-touch-icon.png
DongshouXueShenduXuexiPytorchBan2020313Fix1/img/cancelfullscreen.png
DongshouXueShenduXuexiPytorchBan2020313Fix1/img/close.png
DongshouXueShenduXuexiPytorchBan2020313Fix1/img/fullscreen.png
DongshouXueShenduXuexiPytorchBan2020313Fix1/img/loader.gif
DongshouXueShenduXuexiPytorchBan2020313Fix1/img/menu-icon.png
DongshouXueShenduXuexiPytorchBan2020313Fix1/img/save.png
DongshouXueShenduXuexiPytorchBan2020313Fix1/img/saved.png
DongshouXueShenduXuexiPytorchBan2020313Fix1/img/settings-s.png
DongshouXueShenduXuexiPytorchBan2020313Fix1/img/settings.png
DongshouXueShenduXuexiPytorchBan2020313Fix1/img/star.png
DongshouXueShenduXuexiPytorchBan2020313Fix1/js/__init__.py
DongshouXueShenduXuexiPytorchBan2020313Fix1/js/epub.js
DongshouXueShenduXuexiPytorchBan2020313Fix1/js/epub.min.js
dongshou_xue_shendu_xuexi_pytorch_ban_2020_3_13_fix1-2025.3.24.1.dist-info/METADATA
dongshou_xue_shendu_xuexi_pytorch_ban_2020_3_13_fix1-2025.3.24.1.dist-info/WHEEL
dongshou_xue_shendu_xuexi_pytorch_ban_2020_3_13_fix1-2025.3.24.1.dist-info/entry_points.txt
dongshou_xue_shendu_xuexi_pytorch_ban_2020_3_13_fix1-2025.3.24.1.dist-info/top_level.txt
dongshou_xue_shendu_xuexi_pytorch_ban_2020_3_13_fix1-2025.3.24.1.dist-info/RECORD
